collective/catalogtrace/__init__.py
collective/catalogtrace/configure.zcml
collective/catalogtrace/trace.py
collective_catalogtrace-1.0.3.dist-info/METADATA
collective_catalogtrace-1.0.3.dist-info/WHEEL
collective_catalogtrace-1.0.3.dist-info/entry_points.txt
collective_catalogtrace-1.0.3.dist-info/licenses/LICENSE.GPL
collective_catalogtrace-1.0.3.dist-info/licenses/LICENSE.md
collective_catalogtrace-1.0.3.dist-info/RECORD
